{
  "1": {
    "id": 1,
    "name": "Afghanistan"
  },
  "2": {
    "id": 2,
    "name": "Albania"
  },
  "3": {
    "id": 3,
    "name": "Algeria"
  },
  "4": {
    "id": 4,
    "name": "American Samoa"
  },
  "6": {
    "id": 6,
    "name": "Angola"
  },
  "8": {
    "id": 8,
    "name": "Antigua and Barbuda"
  },
  "9": {
    "id": 9,
    "name": "Argentina",
    "regions": [
      {
        "id": 1,
        "name": "Buenos Aires"
      },
      {
        "id": 2,
        "name": "Ciudad Autónoma de Buenos Aires"
      },
      {
        "id": 3,
        "name": "Catamarca"
      },
      {
        "id": 4,
        "name": "Chaco"
      },
      {
        "id": 5,
        "name": "Chubut"
      },
      {
        "id": 6,
        "name": "Córdoba"
      },
      {
        "id": 7,
        "name": "Corrientes"
      },
      {
        "id": 8,
        "name": "Entre Ríos"
      },
      {
        "id": 9,
        "name": "Formosa"
      },
      {
        "id": 10,
        "name": "Jujuy"
      },
      {
        "id": 11,
        "name": "La Pampa"
      },
      {
        "id": 12,
        "name": "La Rioja"
      },
      {
        "id": 13,
        "name": "Mendoza"
      },
      {
        "id": 14,
        "name": "Misiones"
      },
      {
        "id": 15,
        "name": "Neuquén"
      },
      {
        "id": 16,
        "name": "Río Negro"
      },
      {
        "id": 17,
        "name": "Salta"
      },
      {
        "id": 18,
        "name": "San Juan"
      },
      {
        "id": 19,
        "name": "San Luis"
      },
      {
        "id": 20,
        "name": "Santa Cruz"
      },
      {
        "id": 21,
        "name": "Santa Fe"
      },
      {
        "id": 22,
        "name": "Santiago del Estero"
      },
      {
        "id": 23,
        "name": "Tierra del Fuego"
      },
      {
        "id": 24,
        "name": "Tucumán"
      }
    ]
  },
  "12": {
    "id": 12,
    "name": "Australia",
    "regions": [
      {
        "id": 1,
        "name": "Australian Capital Territory"
      },
      {
        "id": 2,
        "name": "New South Wales"
      },
      {
        "id": 3,
        "name": "Northern Territory"
      },
      {
        "id": 4,
        "name": "Queensland"
      },
      {
        "id": 5,
        "name": "South Australia"
      },
      {
        "id": 6,
        "name": "Tasmania"
      },
      {
        "id": 7,
        "name": "Victoria"
      },
      {
        "id": 8,
        "name": "Western Australia"
      }
    ]
  },
  "13": {
    "id": 13,
    "name": "Austria"
  },
  "15": {
    "id": 15,
    "name": "Bahamas"
  },
  "16": {
    "id": 16,
    "name": "Bahrain"
  },
  "17": {
    "id": 17,
    "name": "Bangladesh"
  },
  "18": {
    "id": 18,
    "name": "Barbados"
  },
  "20": {
    "id": 20,
    "name": "Belgium"
  },
  "21": {
    "id": 21,
    "name": "Belize"
  },
  "22": {
    "id": 22,
    "name": "Benin"
  },
  "25": {
    "id": 25,
    "name": "Bolivia"
  },
  "27": {
    "id": 27,
    "name": "Botswana"
  },
  "28": {
    "id": 28,
    "name": "Brazil",
    "regions": [
      {
        "id": 1,
        "name": "Acre"
      },
      {
        "id": 2,
        "name": "Rondônia"
      },
      {
        "id": 3,
        "name": "Alagoas"
      },
      {
        "id": 4,
        "name": "Amapá"
      },
      {
        "id": 5,
        "name": "Amazonas"
      },
      {
        "id": 6,
        "name": "Bahia"
      },
      {
        "id": 7,
        "name": "Ceará"
      },
      {
        "id": 8,
        "name": "Federal District"
      },
      {
        "id": 9,
        "name": "Espírito Santo"
      },
      {
        "id": 10,
        "name": "Goias"
      },
      {
        "id": 11,
        "name": "Maranhão"
      },
      {
        "id": 12,
        "name": "Mato Grosso"
      },
      {
        "id": 13,
        "name": "Mato Grosso do Sul"
      },
      {
        "id": 14,
        "name": "Minas Gerais"
      },
      {
        "id": 15,
        "name": "Pará"
      },
      {
        "id": 16,
        "name": "Paraíba"
      },
      {
        "id": 17,
        "name": "Paraná"
      },
      {
        "id": 18,
        "name": "Pernambuco"
      },
      {
        "id": 19,
        "name": "Piauí"
      },
      {
        "id": 20,
        "name": "Rio de Janeiro"
      },
      {
        "id": 21,
        "name": "Rio Grande do Sul"
      },
      {
        "id": 22,
        "name": "Rio Grande do Norte"
      },
      {
        "id": 23,
        "name": "Roraima"
      },
      {
        "id": 24,
        "name": "Santa Catarina"
      },
      {
        "id": 25,
        "name": "São Paulo"
      },
      {
        "id": 26,
        "name": "Sergipe"
      },
      {
        "id": 27,
        "name": "Tocantins"
      }
    ]
  },
  "29": {
    "id": 29,
    "name": "British Virgin Islands"
  },
  "31": {
    "id": 31,
    "name": "Bulgaria"
  },
  "33": {
    "id": 33,
    "name": "Burundi"
  },
  "34": {
    "id": 34,
    "name": "Cambodia"
  },
  "35": {
    "id": 35,
    "name": "Cameroon"
  },
  "36": {
    "id": 36,
    "name": "Canada",
    "regions": [
      {
        "id": 1,
        "name": "Alberta"
      },
      {
        "id": 2,
        "name": "British Columbia"
      },
      {
        "id": 3,
        "name": "Manitoba"
      },
      {
        "id": 4,
        "name": "New Brunswick"
      },
      {
        "id": 5,
        "name": "Newfoundland and Labrador"
      },
      {
        "id": 6,
        "name": "Northwest Territories"
      },
      {
        "id": 7,
        "name": "Nova Scotia"
      },
      {
        "id": 8,
        "name": "Nunavut"
      },
      {
        "id": 9,
        "name": "Ontario"
      },
      {
        "id": 10,
        "name": "Prince Edward Island"
      },
      {
        "id": 11,
        "name": "Quebec"
      },
      {
        "id": 12,
        "name": "Saskatchewan"
      },
      {
        "id": 13,
        "name": "Yukon"
      }
    ]
  },
  "40": {
    "id": 40,
    "name": "Chad"
  },
  "42": {
    "id": 42,
    "name": "Chile"
  },
  "43": {
    "id": 43,
    "name": "China",
    "regions": [
      {
        "id": 1,
        "name": "Anhui"
      },
      {
        "id": 2,
        "name": "Beijing"
      },
      {
        "id": 3,
        "name": "Chongqing"
      },
      {
        "id": 4,
        "name": "Fujian"
      },
      {
        "id": 5,
        "name": "Gansu"
      },
      {
        "id": 6,
        "name": "Guangdong"
      },
      {
        "id": 7,
        "name": "Guangxi"
      },
      {
        "id": 8,
        "name": "Guizhou"
      },
      {
        "id": 9,
        "name": "Hainan"
      },
      {
        "id": 10,
        "name": "Hebei"
      },
      {
        "id": 11,
        "name": "Heilongjiang"
      },
      {
        "id": 12,
        "name": "Henan"
      },
      {
        "id": 13,
        "name": "Hubei"
      },
      {
        "id": 14,
        "name": "Hunan"
      },
      {
        "id": 15,
        "name": "Jiangsu"
      },
      {
        "id": 16,
        "name": "Jiangxi"
      },
      {
        "id": 17,
        "name": "Jilin"
      },
      {
        "id": 18,
        "name": "Liaoning"
      },
      {
        "id": 19,
        "name": "Inner Mongolia"
      },
      {
        "id": 20,
        "name": "Ningxia"
      },
      {
        "id": 21,
        "name": "Qinghai"
      },
      {
        "id": 22,
        "name": "Shaanxi"
      },
      {
        "id": 23,
        "name": "Shandong"
      },
      {
        "id": 24,
        "name": "Shanghai"
      },
      {
        "id": 25,
        "name": "Shanxi"
      },
      {
        "id": 26,
        "name": "Sichuan"
      },
      {
        "id": 27,
        "name": "Tianjin"
      },
      {
        "id": 28,
        "name": "Xinjiang"
      },
      {
        "id": 29,
        "name": "Tibet"
      },
      {
        "id": 30,
        "name": "Yunnan"
      },
      {
        "id": 31,
        "name": "Zhejiang"
      },
      {
        "id": 32,
        "name": "Hong Kong"
      },
      {
        "id": 33,
        "name": "Macau"
      }
    ]
  },
  "45": {
    "id": 45,
    "name": "Colombia"
  },
  "47": {
    "id": 47,
    "name": "Congo"
  },
  "48": {
    "id": 48,
    "name": "Cook Islands"
  },
  "49": {
    "id": 49,
    "name": "Costa Rica"
  },
  "51": {
    "id": 51,
    "name": "Croatia"
  },
  "53": {
    "id": 53,
    "name": "Cyprus"
  },
  "54": {
    "id": 54,
    "name": "Czech Republic"
  },
  "58": {
    "id": 58,
    "name": "Denmark"
  },
  "60": {
    "id": 60,
    "name": "Dominica"
  },
  "61": {
    "id": 61,
    "name": "Dominican Republic"
  },
  "62": {
    "id": 62,
    "name": "Ecuador"
  },
  "63": {
    "id": 63,
    "name": "Egypt"
  },
  "64": {
    "id": 64,
    "name": "El Salvador"
  },
  "71": {
    "id": 71,
    "name": "Fiji"
  },
  "72": {
    "id": 72,
    "name": "Finland",
    "regions": [
      {
        "id": 1,
        "name": "Åland Islands"
      },
      {
        "id": 2,
        "name": "Lapland"
      },
      {
        "id": 3,
        "name": "East Finland"
      },
      {
        "id": 4,
        "name": "South Finland"
      },
      {
        "id": 5,
        "name": "Oulu"
      },
      {
        "id": 6,
        "name": "West Finland"
      }
    ]
  },
  "73": {
    "id": 73,
    "name": "France",
    "regions": [
      {
        "id": 1,
        "name": "Aquitaine"
      },
      {
        "id": 2,
        "name": "Alsace"
      },
      {
        "id": 3,
        "name": "Île-de-France"
      },
      {
        "id": 4,
        "name": "Auvergne"
      },
      {
        "id": 5,
        "name": "Corse"
      },
      {
        "id": 6,
        "name": "Champagne-Ardenne"
      },
      {
        "id": 7,
        "name": "Nord-Pas-de-Calais"
      },
      {
        "id": 8,
        "name": "Lower Normandy"
      },
      {
        "id": 9,
        "name": "Upper Normandy"
      },
      {
        "id": 10,
        "name": "Picardy"
      },
      {
        "id": 11,
        "name": "Franche-Comté"
      },
      {
        "id": 12,
        "name": "Burgundy"
      },
      {
        "id": 13,
        "name": "Brittany"
      },
      {
        "id": 14,
        "name": "Provence-Alpes-Côte d'Azur"
      },
      {
        "id": 15,
        "name": "Pays-de-la-Loire"
      },
      {
        "id": 16,
        "name": "Poitou-Charentes"
      },
      {
        "id": 17,
        "name": "Midi-Pyrenees"
      },
      {
        "id": 18,
        "name": "Languedoc-Roussillon"
      },
      {
        "id": 19,
        "name": "Limousin"
      },
      {
        "id": 20,
        "name": "Rhône-Alpes"
      },
      {
        "id": 21,
        "name": "Lorraine"
      },
      {
        "id": 22,
        "name": "Centre"
      }
    ]
  },
  "74": {
    "id": 74,
    "name": "French Guiana"
  },
  "76": {
    "id": 76,
    "name": "Gabon"
  },
  "79": {
    "id": 79,
    "name": "Germany",
    "regions": [
      {
        "id": 1,
        "name": "Baden-Württemberg"
      },
      {
        "id": 2,
        "name": "Bayern"
      },
      {
        "id": 3,
        "name": "Berlin"
      },
      {
        "id": 4,
        "name": "Brandenburg"
      },
      {
        "id": 5,
        "name": "Bremen"
      },
      {
        "id": 6,
        "name": "Hamburg"
      },
      {
        "id": 7,
        "name": "Hesse"
      },
      {
        "id": 8,
        "name": "Mecklenburg-West Pomerania"
      },
      {
        "id": 9,
        "name": "Lower Saxony"
      },
      {
        "id": 10,
        "name": "North Rhine-Westphalia"
      },
      {
        "id": 11,
        "name": "Rhineland-Palatinate"
      },
      {
        "id": 12,
        "name": "Saarland"
      },
      {
        "id": 13,
        "name": "Saxony"
      },
      {
        "id": 14,
        "name": "Saxony-Anhalt"
      },
      {
        "id": 15,
        "name": "Schleswig-Holstein"
      },
      {
        "id": 16,
        "name": "Thuringia"
      }
    ]
  },
  "80": {
    "id": 80,
    "name": "Ghana"
  },
  "81": {
    "id": 81,
    "name": "Gibraltar"
  },
  "82": {
    "id": 82,
    "name": "Greece"
  },
  "83": {
    "id": 83,
    "name": "Greenland"
  },
  "84": {
    "id": 84,
    "name": "Grenada"
  },
  "85": {
    "id": 85,
    "name": "Guadeloupe"
  },
  "87": {
    "id": 87,
    "name": "Guatemala"
  },
  "88": {
    "id": 88,
    "name": "Guinea"
  },
  "90": {
    "id": 90,
    "name": "Guyana"
  },
  "91": {
    "id": 91,
    "name": "Haiti"
  },
  "92": {
    "id": 92,
    "name": "Honduras"
  },
  "93": {
    "id": 93,
    "name": "Hungary"
  },
  "94": {
    "id": 94,
    "name": "Iceland"
  },
  "95": {
    "id": 95,
    "name": "India",
    "regions": [
      {
        "id": 1,
        "name": "Andaman and Nicobar Islands"
      },
      {
        "id": 2,
        "name": "Andhra Pradesh"
      },
      {
        "id": 3,
        "name": "Arunachal Pradesh"
      },
      {
        "id": 4,
        "name": "Assam"
      },
      {
        "id": 5,
        "name": "Bihar"
      },
      {
        "id": 6,
        "name": "Chandigarh"
      },
      {
        "id": 7,
        "name": "Chhattisgarh"
      },
      {
        "id": 8,
        "name": "Dadra and Nagar Haveli"
      },
      {
        "id": 9,
        "name": "Daman and Diu"
      },
      {
        "id": 10,
        "name": "Delhi"
      },
      {
        "id": 11,
        "name": "Goa"
      },
      {
        "id": 12,
        "name": "Gujarat"
      },
      {
        "id": 13,
        "name": "Haryana"
      },
      {
        "id": 14,
        "name": "Himachal Pradesh"
      },
      {
        "id": 15,
        "name": "Jammu and Kashmir"
      },
      {
        "id": 16,
        "name": "Jharkhand"
      },
      {
        "id": 17,
        "name": "Karnataka"
      },
      {
        "id": 18,
        "name": "Kerala"
      },
      {
        "id": 19,
        "name": "Lakshadweep"
      },
      {
        "id": 20,
        "name": "Madhya Pradesh"
      },
      {
        "id": 21,
        "name": "Maharashtra"
      },
      {
        "id": 22,
        "name": "Meghalaya"
      },
      {
        "id": 23,
        "name": "Mizoram"
      },
      {
        "id": 24,
        "name": "Manipur"
      },
      {
        "id": 25,
        "name": "Nagaland"
      },
      {
        "id": 26,
        "name": "Orissa"
      },
      {
        "id": 27,
        "name": "Puducherry"
      },
      {
        "id": 28,
        "name": "Punjab"
      },
      {
        "id": 29,
        "name": "Rajasthan"
      },
      {
        "id": 30,
        "name": "Sikkim"
      },
      {
        "id": 31,
        "name": "Tamil Nadu"
      },
      {
        "id": 32,
        "name": "Tripura"
      },
      {
        "id": 33,
        "name": "Uttar Pradesh"
      },
      {
        "id": 34,
        "name": "Uttarakhand"
      },
      {
        "id": 35,
        "name": "West Bengal"
      }
    ]
  },
  "96": {
    "id": 96,
    "name": "Indonesia"
  },
  "98": {
    "id": 98,
    "name": "Iraq"
  },
  "99": {
    "id": 99,
    "name": "Ireland"
  },
  "101": {
    "id": 101,
    "name": "Israel"
  },
  "102": {
    "id": 102,
    "name": "Italy",
    "regions": [
      {
        "id": 1,
        "name": "Abruzzo"
      },
      {
        "id": 2,
        "name": "Basilicata"
      },
      {
        "id": 3,
        "name": "Calabria"
      },
      {
        "id": 4,
        "name": "Campania"
      },
      {
        "id": 5,
        "name": "Emilia-Romagna"
      },
      {
        "id": 6,
        "name": "Friuli-Venezia Giulia"
      },
      {
        "id": 7,
        "name": "Lazio"
      },
      {
        "id": 8,
        "name": "Liguria"
      },
      {
        "id": 9,
        "name": "Lombardy"
      },
      {
        "id": 10,
        "name": "Marche"
      },
      {
        "id": 11,
        "name": "Molise"
      },
      {
        "id": 12,
        "name": "Piedmont"
      },
      {
        "id": 13,
        "name": "Apulia"
      },
      {
        "id": 14,
        "name": "Sardinia"
      },
      {
        "id": 15,
        "name": "Sicily"
      },
      {
        "id": 16,
        "name": "Tuscany"
      },
      {
        "id": 17,
        "name": "Trentino-Alto Adige"
      },
      {
        "id": 18,
        "name": "Umbria"
      },
      {
        "id": 19,
        "name": "Valle d'Aosta"
      },
      {
        "id": 20,
        "name": "Veneto"
      }
    ]
  },
  "103": {
    "id": 103,
    "name": "Jamaica"
  },
  "105": {
    "id": 105,
    "name": "Japan",
    "regions": [
      {
        "id": 1,
        "name": "Hokkaido (Sapporo)"
      },
      {
        "id": 2,
        "name": "Hokkaido (Hakodate)"
      },
      {
        "id": 3,
        "name": "Hokkaido (Wakkanai)"
      },
      {
        "id": 4,
        "name": "Hokkaido (Kushiro)"
      },
      {
        "id": 5,
        "name": "Aomori"
      },
      {
        "id": 6,
        "name": "Iwate"
      },
      {
        "id": 7,
        "name": "Miyagi"
      },
      {
        "id": 8,
        "name": "Akita"
      },
      {
        "id": 9,
        "name": "Yamagata"
      },
      {
        "id": 10,
        "name": "Fukushima"
      },
      {
        "id": 11,
        "name": "Ibaraki"
      },
      {
        "id": 12,
        "name": "Tochigi"
      },
      {
        "id": 13,
        "name": "Gunma"
      },
      {
        "id": 14,
        "name": "Saitama"
      },
      {
        "id": 15,
        "name": "Chiba"
      },
      {
        "id": 16,
        "name": "Tokyo"
      },
      {
        "id": 17,
        "name": "Kanagawa"
      },
      {
        "id": 18,
        "name": "Niigata"
      },
      {
        "id": 19,
        "name": "Toyama"
      },
      {
        "id": 20,
        "name": "Ishikawa"
      },
      {
        "id": 21,
        "name": "Fukui"
      },
      {
        "id": 22,
        "name": "Yamanashi"
      },
      {
        "id": 23,
        "name": "Nagano"
      },
      {
        "id": 24,
        "name": "Gifu"
      },
      {
        "id": 25,
        "name": "Shizuoka"
      },
      {
        "id": 26,
        "name": "Aichi"
      },
      {
        "id": 27,
        "name": "Mie"
      },
      {
        "id": 28,
        "name": "Shiga"
      },
      {
        "id": 29,
        "name": "Kyoto"
      },
      {
        "id": 30,
        "name": "Osaka"
      },
      {
        "id": 31,
        "name": "Hyogo"
      },
      {
        "id": 32,
        "name": "Nara"
      },
      {
        "id": 33,
        "name": "Wakayama"
      },
      {
        "id": 34,
        "name": "Tottori"
      },
      {
        "id": 35,
        "name": "Shimane"
      },
      {
        "id": 36,
        "name": "Okayama"
      },
      {
        "id": 37,
        "name": "Hiroshima"
      },
      {
        "id": 38,
        "name": "Yamaguchi"
      },
      {
        "id": 39,
        "name": "Tokushima"
      },
      {
        "id": 40,
        "name": "Kagawa"
      },
      {
        "id": 41,
        "name": "Ehime"
      },
      {
        "id": 42,
        "name": "Kochi"
      },
      {
        "id": 43,
        "name": "Fukuoka"
      },
      {
        "id": 44,
        "name": "Saga"
      },
      {
        "id": 45,
        "name": "Nagasaki"
      },
      {
        "id": 46,
        "name": "Kumamoto"
      },
      {
        "id": 47,
        "name": "Oita"
      },
      {
        "id": 48,
        "name": "Miyazaki"
      },
      {
        "id": 49,
        "name": "Kagoshima"
      },
      {
        "id": 50,
        "name": "Okinawa"
      }
    ]
  },
  "106": {
    "id": 106,
    "name": "Jordan"
  },
  "109": {
    "id": 109,
    "name": "Kenya"
  },
  "111": {
    "id": 111,
    "name": "Kuwait"
  },
  "115": {
    "id": 115,
    "name": "Lebanon"
  },
  "117": {
    "id": 117,
    "name": "Liberia"
  },
  "118": {
    "id": 118,
    "name": "Libya"
  },
  "121": {
    "id": 121,
    "name": "Luxembourg"
  },
  "125": {
    "id": 125,
    "name": "Malaysia"
  },
  "128": {
    "id": 128,
    "name": "Malta"
  },
  "131": {
    "id": 131,
    "name": "Mauritania"
  },
  "132": {
    "id": 132,
    "name": "Mauritius"
  },
  "134": {
    "id": 134,
    "name": "Mexico"
  },
  "138": {
    "id": 138,
    "name": "Montenegro"
  },
  "139": {
    "id": 139,
    "name": "Morocco"
  },
  "141": {
    "id": 141,
    "name": "Myanmar"
  },
  "145": {
    "id": 145,
    "name": "Netherlands"
  },
  "147": {
    "id": 147,
    "name": "New Caledonia"
  },
  "148": {
    "id": 148,
    "name": "New Zealand"
  },
  "149": {
    "id": 149,
    "name": "Nicaragua"
  },
  "150": {
    "id": 150,
    "name": "Niger"
  },
  "151": {
    "id": 151,
    "name": "Nigeria"
  },
  "155": {
    "id": 155,
    "name": "Norway",
    "regions": [
      {
        "id": 1,
        "name": "Akershus"
      },
      {
        "id": 2,
        "name": "Aust-Agder"
      },
      {
        "id": 3,
        "name": "Buskerud"
      },
      {
        "id": 4,
        "name": "Finnmark"
      },
      {
        "id": 5,
        "name": "Hedmark"
      },
      {
        "id": 6,
        "name": "Hordaland"
      },
      {
        "id": 7,
        "name": "Jan Mayen Island"
      },
      {
        "id": 8,
        "name": "Lofoten"
      },
      {
        "id": 9,
        "name": "Møre og Romsdal"
      },
      {
        "id": 10,
        "name": "Nordland"
      },
      {
        "id": 11,
        "name": "Nord-Trøndelag"
      },
      {
        "id": 12,
        "name": "Oppland"
      },
      {
        "id": 13,
        "name": "Oslo"
      },
      {
        "id": 14,
        "name": "Rogaland"
      },
      {
        "id": 15,
        "name": "Sogn og Fjordane"
      },
      {
        "id": 16,
        "name": "Sør-Trøndelag"
      },
      {
        "id": 17,
        "name": "Svalbard"
      },
      {
        "id": 18,
        "name": "Telemark"
      },
      {
        "id": 19,
        "name": "Troms"
      },
      {
        "id": 20,
        "name": "Vest-Agder"
      },
      {
        "id": 21,
        "name": "Vestfold"
      },
      {
        "id": 22,
        "name": "Østfold"
      }
    ]
  },
  "156": {
    "id": 156,
    "name": "Oman"
  },
  "157": {
    "id": 157,
    "name": "Pakistan"
  },
  "160": {
    "id": 160,
    "name": "Panama"
  },
  "161": {
    "id": 161,
    "name": "Papua New Guinea"
  },
  "163": {
    "id": 163,
    "name": "Peru"
  },
  "164": {
    "id": 164,
    "name": "Philippines"
  },
  "166": {
    "id": 166,
    "name": "Poland",
    "regions": [
      {
        "id": 1,
        "name": "Lower Silesia"
      },
      {
        "id": 2,
        "name": "Kuyavia-Pomerania"
      },
      {
        "id": 3,
        "name": "Lublin"
      },
      {
        "id": 4,
        "name": "Lubusz"
      },
      {
        "id": 5,
        "name": "Lodz"
      },
      {
        "id": 6,
        "name": "Lesser Poland"
      },
      {
        "id": 7,
        "name": "Masovia"
      },
      {
        "id": 8,
        "name": "Opole"
      },
      {
        "id": 9,
        "name": "Subcarpathia"
      },
      {
        "id": 10,
        "name": "Podlachia"
      },
      {
        "id": 11,
        "name": "Pomerania"
      },
      {
        "id": 12,
        "name": "Silesia"
      },
      {
        "id": 13,
        "name": "Holy Cross"
      },
      {
        "id": 14,
        "name": "Warmia-Masuria"
      },
      {
        "id": 15,
        "name": "Greater Poland"
      },
      {
        "id": 16,
        "name": "West Pomerania"
      }
    ]
  },
  "167": {
    "id": 167,
    "name": "Portugal"
  },
  "170": {
    "id": 170,
    "name": "South Korea"
  },
  "173": {
    "id": 173,
    "name": "Romania"
  },
  "174": {
    "id": 174,
    "name": "Russian Federation",
    "regions": [
      {
        "id": 1,
        "name": "Central Federal District"
      },
      {
        "id": 2,
        "name": "Far Eastern Federal District"
      },
      {
        "id": 3,
        "name": "Northwestern Federal District"
      },
      {
        "id": 4,
        "name": "Volga Federal District"
      },
      {
        "id": 5,
        "name": "Siberian Federal District"
      },
      {
        "id": 6,
        "name": "Southern Federal District"
      },
      {
        "id": 7,
        "name": "Urals Federal District"
      },
      {
        "id": 8,
        "name": "North Caucasian Federal District"
      }
    ]
  },
  "181": {
    "id": 181,
    "name": "Samoa"
  },
  "185": {
    "id": 185,
    "name": "Senegal"
  },
  "186": {
    "id": 186,
    "name": "Serbia"
  },
  "188": {
    "id": 188,
    "name": "Sierra Leone"
  },
  "189": {
    "id": 189,
    "name": "Singapore"
  },
  "190": {
    "id": 190,
    "name": "Slovakia"
  },
  "191": {
    "id": 191,
    "name": "Slovenia"
  },
  "194": {
    "id": 194,
    "name": "South Africa"
  },
  "195": {
    "id": 195,
    "name": "Spain",
    "regions": [
      {
        "id": 1,
        "name": "Andalusia"
      },
      {
        "id": 2,
        "name": "Aragon"
      },
      {
        "id": 3,
        "name": "Asturias"
      },
      {
        "id": 4,
        "name": "Balearic Islands"
      },
      {
        "id": 5,
        "name": "Basque Country"
      },
      {
        "id": 6,
        "name": "Canary Islands"
      },
      {
        "id": 7,
        "name": "Cantabria"
      },
      {
        "id": 8,
        "name": "Castile-La Mancha"
      },
      {
        "id": 9,
        "name": "Castile and León"
      },
      {
        "id": 10,
        "name": "Catalonia"
      },
      {
        "id": 11,
        "name": "Extremadura"
      },
      {
        "id": 12,
        "name": "Galicia"
      },
      {
        "id": 13,
        "name": "Madrid"
      },
      {
        "id": 14,
        "name": "Murcia"
      },
      {
        "id": 15,
        "name": "Navarre"
      },
      {
        "id": 16,
        "name": "La Rioja"
      },
      {
        "id": 17,
        "name": "Valencia"
      }
    ]
  },
  "196": {
    "id": 196,
    "name": "Sri Lanka"
  },
  "198": {
    "id": 198,
    "name": "Suriname"
  },
  "199": {
    "id": 199,
    "name": "Swaziland"
  },
  "200": {
    "id": 200,
    "name": "Sweden",
    "regions": [
      {
        "id": 1,
        "name": "Blekinge"
      },
      {
        "id": 2,
        "name": "Dalarna"
      },
      {
        "id": 3,
        "name": "Gävleborg"
      },
      {
        "id": 4,
        "name": "Gotland"
      },
      {
        "id": 5,
        "name": "Halland"
      },
      {
        "id": 6,
        "name": "Jamtland"
      },
      {
        "id": 7,
        "name": "Jönköping"
      },
      {
        "id": 8,
        "name": "Kalmar"
      },
      {
        "id": 9,
        "name": "Kronoberg"
      },
      {
        "id": 10,
        "name": "Norrbotten"
      },
      {
        "id": 11,
        "name": "Oland"
      },
      {
        "id": 12,
        "name": "Örebro"
      },
      {
        "id": 13,
        "name": "Östergötland"
      },
      {
        "id": 14,
        "name": "Skane"
      },
      {
        "id": 15,
        "name": "Sodermanland"
      },
      {
        "id": 16,
        "name": "Stockholm"
      },
      {
        "id": 17,
        "name": "Uppsala"
      },
      {
        "id": 18,
        "name": "Varmland"
      },
      {
        "id": 19,
        "name": "Vasterbotten"
      },
      {
        "id": 20,
        "name": "Västernorrland"
      },
      {
        "id": 21,
        "name": "Vastmanland"
      },
      {
        "id": 22,
        "name": "Västra Götaland"
      }
    ]
  },
  "201": {
    "id": 201,
    "name": "Switzerland"
  },
  "203": {
    "id": 203,
    "name": "Taiwan"
  },
  "205": {
    "id": 205,
    "name": "Thailand"
  },
  "206": {
    "id": 206,
    "name": "Togo"
  },
  "210": {
    "id": 210,
    "name": "Tunisia"
  },
  "211": {
    "id": 211,
    "name": "Turkey"
  },
  "215": {
    "id": 215,
    "name": "Uganda"
  },
  "217": {
    "id": 217,
    "name": "United Arab Emirates"
  },
  "218": {
    "id": 218,
    "name": "United Kingdom",
    "regions": [
      {
        "id": 1,
        "name": "East of England"
      },
      {
        "id": 2,
        "name": "East Midlands"
      },
      {
        "id": 3,
        "name": "Greater London"
      },
      {
        "id": 4,
        "name": "North East England"
      },
      {
        "id": 5,
        "name": "North West England"
      },
      {
        "id": 6,
        "name": "Northern Ireland"
      },
      {
        "id": 7,
        "name": "Scotland"
      },
      {
        "id": 8,
        "name": "South East England"
      },
      {
        "id": 9,
        "name": "South West England"
      },
      {
        "id": 10,
        "name": "Wales"
      },
      {
        "id": 11,
        "name": "West Midlands"
      },
      {
        "id": 12,
        "name": "Yorkshire and the Humber"
      }
    ]
  },
  "219": {
    "id": 219,
    "name": "Tanzania"
  },
  "220": {
    "id": 220,
    "name": "United States of America",
    "regions": [
      {
        "id": 1,
        "name": "Alabama"
      },
      {
        "id": 2,
        "name": "Alaska"
      },
      {
        "id": 3,
        "name": "Arizona"
      },
      {
        "id": 4,
        "name": "Arkansas"
      },
      {
        "id": 5,
        "name": "California"
      },
      {
        "id": 6,
        "name": "Colorado"
      },
      {
        "id": 7,
        "name": "Connecticut"
      },
      {
        "id": 8,
        "name": "Delaware"
      },
      {
        "id": 9,
        "name": "Florida"
      },
      {
        "id": 10,
        "name": "Georgia"
      },
      {
        "id": 11,
        "name": "Hawaii"
      },
      {
        "id": 12,
        "name": "Idaho"
      },
      {
        "id": 13,
        "name": "Illinois"
      },
      {
        "id": 14,
        "name": "Indiana"
      },
      {
        "id": 15,
        "name": "Iowa"
      },
      {
        "id": 16,
        "name": "Kansas"
      },
      {
        "id": 17,
        "name": "Kentucky"
      },
      {
        "id": 18,
        "name": "Louisiana"
      },
      {
        "id": 19,
        "name": "Maine"
      },
      {
        "id": 20,
        "name": "Maryland"
      },
      {
        "id": 21,
        "name": "Massachusetts"
      },
      {
        "id": 22,
        "name": "Michigan"
      },
      {
        "id": 23,
        "name": "Minnesota"
      },
      {
        "id": 24,
        "name": "Mississippi"
      },
      {
        "id": 25,
        "name": "Missouri"
      },
      {
        "id": 26,
        "name": "Montana"
      },
      {
        "id": 27,
        "name": "Nebraska"
      },
      {
        "id": 28,
        "name": "Nevada"
      },
      {
        "id": 29,
        "name": "New Hampshire"
      },
      {
        "id": 30,
        "name": "New Jersey"
      },
      {
        "id": 31,
        "name": "New Mexico"
      },
      {
        "id": 32,
        "name": "New York"
      },
      {
        "id": 33,
        "name": "North Carolina"
      },
      {
        "id": 34,
        "name": "North Dakota"
      },
      {
        "id": 35,
        "name": "Ohio"
      },
      {
        "id": 36,
        "name": "Oklahoma"
      },
      {
        "id": 37,
        "name": "Oregon"
      },
      {
        "id": 38,
        "name": "Pennsylvania"
      },
      {
        "id": 39,
        "name": "Rhode Island"
      },
      {
        "id": 40,
        "name": "South Carolina"
      },
      {
        "id": 41,
        "name": "South Dakota"
      },
      {
        "id": 42,
        "name": "Tennessee"
      },
      {
        "id": 43,
        "name": "Texas"
      },
      {
        "id": 44,
        "name": "Utah"
      },
      {
        "id": 45,
        "name": "Vermont"
      },
      {
        "id": 46,
        "name": "Virginia"
      },
      {
        "id": 47,
        "name": "Washington"
      },
      {
        "id": 48,
        "name": "Washington, DC"
      },
      {
        "id": 49,
        "name": "West Virginia"
      },
      {
        "id": 50,
        "name": "Wisconsin"
      },
      {
        "id": 51,
        "name": "Wyoming"
      }
    ]
  },
  "221": {
    "id": 221,
    "name": "United States Virgin Islands"
  },
  "222": {
    "id": 222,
    "name": "Uruguay"
  },
  "224": {
    "id": 224,
    "name": "Vanuatu"
  },
  "226": {
    "id": 226,
    "name": "Venezuela"
  },
  "227": {
    "id": 227,
    "name": "Vietnam"
  }
}